<?xml version="1.0" encoding="utf-8"?>
<!DOCTYPE hibernate-mapping PUBLIC "-//Hibernate/Hibernate Mapping DTD 3.0//EN"
"http://hibernate.sourceforge.net/hibernate-mapping-3.0.dtd">
<!-- 
    Mapping file autogenerated by MyEclipse Persistence Tools
-->
<hibernate-mapping>
    <class name="cmc.com.ktnb.entity.TTKT.tien_hanh_ttkt.TtktThCongBoQd" table="TTKT_TH_CONG_BO_QD" schema="KTNB_OWNER">
        <id name="id" type="java.lang.String">
            <column name="ID" length="40" />
            <generator class="assigned" />
        </id>
        <property name="idCuocTtkt" type="java.lang.String">
            <column name="ID_CUOC_TTKT" length="40" not-null="true" />
        </property>
        <property name="thoiDiemCbTu" type="java.util.Date">
            <column name="THOI_DIEM_CB_TU" length="7" not-null="true" />
        </property>
        <property name="thoiDiemCbDen" type="java.util.Date">
            <column name="THOI_DIEM_CB_DEN" length="7" not-null="true" />
        </property>
        <property name="idDaiDienCqBanHanhQd" type="java.lang.String">
            <column name="ID_DAI_DIEN_CQ_BAN_HANH_QD" length="40" />
        </property>
        <property name="ykienPhatBieu" type="java.lang.String">
            <column name="Y_KIEN_PHAT_BIEU" length="2000" />
        </property>
        <property name="diaDiem" type="java.lang.String">
            <column name="DIA_DIEM" not-null="true" />
        </property>
        <property name="idDaiDienCqqlCapTren" type="java.lang.String">
            <column name="ID_DAI_DIEN_CQQL_CAP_TREN" length="40" />
        </property>
        <property name="idDaiDienDoanTtkt" type="java.lang.String">
            <column name="ID_DAI_DIEN_DOAN_TTKT" length="40" />
        </property>
        <property name="idDaiDienDonViDuocTtkt" type="java.lang.String">
            <column name="ID_DAI_DIEN_DON_VI_DUOC_TTKT" length="40" />
        </property>
        <property name="idNguoiCapNat" type="java.lang.String">
            <column name="ID_NGUOI_CAP_NHAT" length="40"/>
        </property>
          <property name="tenNguoiCapNhat" type="java.lang.String">
            <column name="TEN_NGUOI_CAP_NHAP" length="200"/>
        </property>
        <property name="ngayCapNhat" type="java.util.Date">
            <column name="NGAY_CAP_NHAT" length="7" />
        </property>
    </class>
</hibernate-mapping>
