<?xml version="1.0" encoding="utf-8"?>
<!DOCTYPE hibernate-mapping PUBLIC "-//Hibernate/Hibernate Mapping DTD 3.0//EN"
"http://hibernate.sourceforge.net/hibernate-mapping-3.0.dtd">
<!-- 
    Mapping file autogenerated by MyEclipse Persistence Tools
-->
<hibernate-mapping>
    <class name="cmc.com.ktnb.entity.TTKT.chuan_bi_tien_hanh.TtktCbHoan" table="TTKT_CB_HOAN" schema="KTNB_OWNER">
        <id name="id" type="java.lang.String">
            <column name="ID" length="40" />
            <generator class="assigned" />
        </id>
        <property name="idCuocTtkt" type="java.lang.String">
            <column name="ID_CUOC_TTKT" length="40" not-null="true" />
        </property>
        <property name="cqtDeNghi" type="java.lang.Boolean">
            <column name="CQT_DE_NGHI" precision="1" scale="0" not-null="true" />
        </property>
        <property name="ngayHoan" type="java.util.Date">
            <column name="NGAY_HOAN" length="7" not-null="true" />
        </property>
        <property name="ngayBatDauLai" type="java.util.Date">
            <column name="NGAY_BAT_DAU_LAI" length="7" not-null="true" />
        </property>
        <property name="lyDoHoan" type="java.lang.String">
            <column name="LY_DO_HOAN" />
        </property>
        
        <property name="tenFileVbXinHoan" type="java.lang.String">
            <column name="TEN_FILE_VB_XIN_HOAN" />
        </property>
        <property name="loaiFileVbXinHoan" type="java.lang.String">
            <column name="LOAI_FILE_VB_XIN_HOAN" />
        </property>
        
        <property name="tenFileVbTraLoiHoan" type="java.lang.String">
            <column name="TEN_FILE_VB_TRA_LOI_HOAN" />
        </property>
        <property name="loaiFileVbTraLoiHoan" type="java.lang.String">
            <column name="LOAI_FILE_VB_TRA_LOI_HOAN" />
        </property>
        
        <property name="vbXinHoanCuaDvDuocTtkt" type="java.lang.String">
            <column name="VB_XIN_HOAN_CUA_DV_DUOC_TTKT" />
        </property>
        <property name="vbTraLoiCuaDvTh" type="java.lang.String">
            <column name="VB_TRA_LOI_CUA_DV_TH" />
        </property>
        <property name="trangThai" type="java.lang.Boolean">
            <column name="TRANG_THAI" precision="1" scale="0" />
        </property>
        <property name="ngayBatDauThucTe" type="java.util.Date">
            <column name="NGAY_BAT_DAU_THUC_TE" length="7" />
        </property>
        <property name="idVbXinHoan" type="java.lang.String">
            <column name="ID_VB_XIN_HOAN" length="240" />
        </property>
        <property name="idVbTraLoi" type="java.lang.String">
            <column name="ID_VB_TRA_LOI" length="240" />
        </property>
        <property name="idVbThongBaoHoan" type="java.lang.String">
            <column name="ID_VB_THONG_BAO_HOAN" length="240" />
        </property>
        <property name="tenFileThongBaoHoan" type="java.lang.String">
            <column name="TEN_FILE_THONG_BAO_HOAN" />
        </property>
        <property name="loaiFileThongBaoHoan" type="java.lang.String">
            <column name="LOAI_FILE_THONG_BAO_HOAN" />
        </property>
        <property name="vbThongBaoHoan" type="java.lang.String">
            <column name="VB_THONG_BAO_HOAN" />
        </property>
        
        <property name="idNguoiCapNat" type="java.lang.String">
            <column name="ID_NGUOI_CAP_NHAT" length="40"/>
        </property>
          <property name="tenNguoiCapNhat" type="java.lang.String">
            <column name="TEN_NGUOI_CAP_NHAP" length="200"/>
        </property>
        <property name="ngayCapNhat" type="java.util.Date">
            <column name="NGAY_CAP_NHAT" length="7" />
        </property>
    </class>
</hibernate-mapping>
