<?xml version="1.0" encoding="utf-8"?>
<!DOCTYPE hibernate-mapping PUBLIC "-//Hibernate/Hibernate Mapping DTD 3.0//EN"
"http://hibernate.sourceforge.net/hibernate-mapping-3.0.dtd">
<!-- 
    Mapping file autogenerated by MyEclipse Persistence Tools  
-->
<hibernate-mapping>
    <class name="cmc.com.ktnb.entity.TTKT.tien_hanh_ttkt.TtktThQdNiemPhongHsTl" table="TTKT_TH_QD_NIEM_PHONG_HS_TL" schema="KTNB_OWNER">
        <id name="id" type="java.lang.String">
            <column name="ID" length="40" />
            <generator class="assigned" />
        </id>
        <property name="idCuocTtkt" type="java.lang.String">
            <column name="ID_CUOC_TTKT" length="40" not-null="true" />
        </property>
         <property name="idDsTvdQdNiemPhong" type="java.lang.String">
            <column name="ID_DS_TVD_QD_NP" length="40"/>
        </property>
        <property name="idDsTvdQdMoNiemPhong" type="java.lang.String">
            <column name="ID_DS_TVD_QD_MNP" length="40"/>
        </property>
        <property name="ngayRaQd" type="java.util.Date">
            <column name="NGAY_RA_QD" length="7"  />
        </property>
        <property name="taiLieuDuocNiemPhong" type="java.lang.String">
            <column name="TAI_LIEU_DUOC_NIEM_PHONG"  />
        </property>
        <property name="tgNiemPhongTu" type="java.util.Date">
            <column name="TG_NIEM_PHONG_TU" length="7"  />
        </property>
        <property name="idDviCnhanThucHien" type="java.lang.String">
            <column name="ID_DVI_CNHAN_THUC_HIEN" length="40" />
        </property>
        <property name="idDviCnhanBaoQuan" type="java.lang.String">
            <column name="ID_DVI_CNHAN_BAO_QUAN" length="40" />
        </property>
        <property name="tenDviCnhanBaoQuan" type="java.lang.String">
            <column name="TEN_DVI_CNHAN_BAO_QUAN" length="7"  />
        </property>
        <property name="noiRaQd" type="java.lang.String">
            <column name="NOI_RA_QD" not-null="true" />
        </property>
        <property name="chucVuDviCnhanThucHien" type="java.lang.String">
            <column name="CHUC_VU_DVI_CNHAN_THUC_HIEN" />
        </property>
        <property name="idCnhanBaoQuanSauMo" type="java.lang.String">
            <column name="ID_CNHAN_BAO_QUAN_SAU_MO" length="40" />
        </property>
        <property name="idNguoiMoNiemPhong" type="java.lang.String">
            <column name="ID_NGUOI_MO_NIEM_PHONG" length="40" />
        </property>
        <property name="tenNguoiMoNiemPhong" type="java.lang.String">
            <column name="TEN_NGUOI_MO_NIEM_PHONG" />
        </property>
        <property name="chucVuNguoiMoNiemPhong" type="java.lang.String">
            <column name="CHUC_VU_NGUOI_MO_NIEM_PHONG" />
        </property>
        <property name="tenDviCnhanThucHien" type="java.lang.String">
            <column name="TEN_DVI_CNHAN_THUC_HIEN"  />
        </property>
        <property name="noiRaQdMoNp" type="java.lang.String">
            <column name="NOI_RA_QD_MO_NP" />
        </property>
        <property name="ngayRaQdMoNp" type="java.util.Date">
            <column name="NGAY_RA_QD_MO_NP" length="7" />
        </property>
        <property name="tenDviCnhanBaoQuanSauMo" type="java.lang.String">
            <column name="TEN_DVI_CNHAN_BAO_QUAN_SAU_MO"  />
        </property>
       <property name="idNguoiCapNat" type="java.lang.String">
            <column name="ID_NGUOI_CAP_NHAT" length="40"/>
        </property>
          <property name="tenNguoiCapNhat" type="java.lang.String">
            <column name="TEN_NGUOI_CAP_NHAP" length="200"/>
        </property>
        <property name="ngayCapNhat" type="java.util.Date">
            <column name="NGAY_CAP_NHAT" length="7" />
        </property>
        <property name="canCuQd" type="java.lang.String">
            <column name="CAN_CU_QD" length="100" />
        </property>
    </class>
</hibernate-mapping>
